{
  "id": "gwen",
  "name": "灵罗娃娃",
  "alias": "Gwen",
  "key": 887,
  "title": "格温",
  "skins": [
    {
      "id": 887039,
      "name": "青蛙雨衣 格温",
      "roitName": "Rain Shepherd Gwen",
      "sortName": null,
      "rarity": "史诗",
      "raritySubType": null,
      "price": null,
      "priceUnit": null,
      "skinline": "青蛙雨衣",
      "universe": "",
      "pushDate": "2025年11月19日",
      "splashPath": "https://raw.communitydragon.org/latest/plugins/rcp-be-lol-game-data/global/default/assets/characters/gwen/skins/skin39/images/gwen_splash_uncentered_39.skins_gwen_skin39.jpg",
      "splashHDPath": "",
      "squareePath": "https://raw.communitydragon.org/latest/plugins/rcp-be-lol-game-data/global/default/assets/characters/gwen/skins/skin39/images/gwen_splash_tile_39.skins_gwen_skin39.jpg",
      "iconPath": "",
      "centeredPath": "https://raw.communitydragon.org/latest/plugins/rcp-be-lol-game-data/global/default/assets/characters/gwen/skins/skin39/images/gwen_splash_centered_39.skins_gwen_skin39.jpg",
      "circlePath": "",
      "chromaPath": "https://raw.communitydragon.org/latest/plugins/rcp-be-lol-game-data/global/default/v1/champion-chroma-images/887/887039.png",
      "specialEditionPath": null,
      "loadingPath": "https://raw.communitydragon.org/latest/plugins/rcp-be-lol-game-data/global/default/assets/characters/gwen/skins/skin39/gwenloadscreen_39.skins_gwen_skin39.jpg",
      "loadingSpecialEditionPath": "",
      "backstory": "格温是牧雨者们开朗活泼的首席裁缝。在雨停之前，她作为魔法裁缝的才能没有得到充分发挥，但无休止的干旱却给了她新的生命。新的想法如洪流般涌现，比如透气的保水织物。现在她通过设计能让青蛙朋友们保持精神饱满、水分充足的湿衣来帮助它们。",
      "accessories": [],
      "roit": {
        "price": 1350,
        "priceType": "直售",
        "priceStartDay": "",
        "priceEndDay": "",
        "description": ""
      },
      "tencentPrice": 8900,
      "icon": "",
      "tencent": {
        "price": 8900,
        "priceType": "直售",
        "priceTypeChinese": "",
        "priceStartDay": "2025年11月20日版本更新后",
        "priceEndDay": "长期销售",
        "description": ""
      },
      "chromas": [
        {
          "id": 887040,
          "name": "青蛙雨衣 格温 红雨",
          "sortName": "红雨",
          "colorName": "红色",
          "tencent": {
            "price": 0,
            "priceType": "暂无",
            "priceStartDay": "",
            "priceEndDay": "",
            "description": "",
            "wildRiftSell": {
              "startDate": "",
              "endDate": "",
              "description": "",
              "activityTitle": "",
              "price": "",
              "priceUnit": ""
            }
          },
          "roit": {
            "price": 290,
            "priceType": "礼包",
            "priceStartDay": "",
            "priceEndDay": "",
            "description": ""
          },
          "riotName": "青蛙雨衣 格温 红雨",
          "chromasPath": "https://raw.communitydragon.org/latest/plugins/rcp-be-lol-game-data/global/default/v1/champion-chroma-images/887/887040.png",
          "mythicIcon": null,
          "wildRiftSell": {
            "startDate": "",
            "endDate": "",
            "description": "",
            "activityTitle": "",
            "price": "",
            "priceUnit": ""
          },
          "colors": [
            "#D33528",
            "#D33528"
          ]
        },
        {
          "id": 887041,
          "name": "青蛙雨衣 格温 沁雨",
          "sortName": "沁雨",
          "colorName": "黄色",
          "tencent": {
            "price": 0,
            "priceType": "暂无",
            "priceStartDay": "",
            "priceEndDay": "",
            "description": "",
            "wildRiftSell": {
              "startDate": "",
              "endDate": "",
              "description": "",
              "activityTitle": "",
              "price": "",
              "priceUnit": ""
            }
          },
          "roit": {
            "price": 290,
            "priceType": "直售",
            "priceStartDay": "",
            "priceEndDay": "",
            "description": ""
          },
          "riotName": "青蛙雨衣 格温 沁雨",
          "chromasPath": "https://raw.communitydragon.org/latest/plugins/rcp-be-lol-game-data/global/default/v1/champion-chroma-images/887/887041.png",
          "mythicIcon": null,
          "wildRiftSell": {
            "startDate": "",
            "endDate": "",
            "description": "",
            "activityTitle": "",
            "price": "",
            "priceUnit": ""
          },
          "colors": [
            "#FFEE59",
            "#FFEE59"
          ]
        },
        {
          "id": 887042,
          "name": "青蛙雨衣 格温 烟雨",
          "sortName": "烟雨",
          "colorName": "青色",
          "tencent": {
            "price": 0,
            "priceType": "暂无",
            "priceStartDay": "",
            "priceEndDay": "",
            "description": "",
            "wildRiftSell": {
              "startDate": "",
              "endDate": "",
              "description": "",
              "activityTitle": "",
              "price": "",
              "priceUnit": ""
            }
          },
          "roit": {
            "price": 290,
            "priceType": "直售",
            "priceStartDay": "",
            "priceEndDay": "",
            "description": ""
          },
          "riotName": "青蛙雨衣 格温 烟雨",
          "chromasPath": "https://raw.communitydragon.org/latest/plugins/rcp-be-lol-game-data/global/default/v1/champion-chroma-images/887/887042.png",
          "mythicIcon": null,
          "wildRiftSell": {
            "startDate": "",
            "endDate": "",
            "description": "",
            "activityTitle": "",
            "price": "",
            "priceUnit": ""
          },
          "colors": [
            "#73BFBE",
            "#73BFBE"
          ]
        },
        {
          "id": 887043,
          "name": "青蛙雨衣 格温 梦雨",
          "sortName": "梦雨",
          "colorName": "紫色",
          "tencent": {
            "price": 0,
            "priceType": "暂无",
            "priceStartDay": "",
            "priceEndDay": "",
            "description": "",
            "wildRiftSell": {
              "startDate": "",
              "endDate": "",
              "description": "",
              "activityTitle": "",
              "price": "",
              "priceUnit": ""
            }
          },
          "roit": {
            "price": 290,
            "priceType": "直售",
            "priceStartDay": "",
            "priceEndDay": "",
            "description": ""
          },
          "riotName": "青蛙雨衣 格温 梦雨",
          "chromasPath": "https://raw.communitydragon.org/latest/plugins/rcp-be-lol-game-data/global/default/v1/champion-chroma-images/887/887043.png",
          "mythicIcon": null,
          "wildRiftSell": {
            "startDate": "",
            "endDate": "",
            "description": "",
            "activityTitle": "",
            "price": "",
            "priceUnit": ""
          },
          "colors": [
            "#9C68D7",
            "#9C68D7"
          ]
        },
        {
          "id": 887044,
          "name": "青蛙雨衣 格温 豪雨",
          "sortName": "豪雨",
          "colorName": "蓝色",
          "tencent": {
            "price": 0,
            "priceType": "暂无",
            "priceStartDay": "",
            "priceEndDay": "",
            "description": "",
            "wildRiftSell": {
              "startDate": "",
              "endDate": "",
              "description": "",
              "activityTitle": "",
              "price": "",
              "priceUnit": ""
            }
          },
          "roit": {
            "price": 290,
            "priceType": "直售",
            "priceStartDay": "",
            "priceEndDay": "",
            "description": ""
          },
          "riotName": "青蛙雨衣 格温 豪雨",
          "chromasPath": "https://raw.communitydragon.org/latest/plugins/rcp-be-lol-game-data/global/default/v1/champion-chroma-images/887/887044.png",
          "mythicIcon": null,
          "wildRiftSell": {
            "startDate": "",
            "endDate": "",
            "description": "",
            "activityTitle": "",
            "price": "",
            "priceUnit": ""
          },
          "colors": [
            "#6ABBEE",
            "#6ABBEE"
          ]
        },
        {
          "id": 887045,
          "name": "青蛙雨衣 格温 桃雨",
          "sortName": "桃雨",
          "colorName": "粉色",
          "tencent": {
            "price": 0,
            "priceType": "暂无",
            "priceStartDay": "",
            "priceEndDay": "",
            "description": "",
            "wildRiftSell": {
              "startDate": "",
              "endDate": "",
              "description": "",
              "activityTitle": "",
              "price": "",
              "priceUnit": ""
            }
          },
          "roit": {
            "price": 290,
            "priceType": "直售",
            "priceStartDay": "",
            "priceEndDay": "",
            "description": ""
          },
          "riotName": "青蛙雨衣 格温 桃雨",
          "chromasPath": "https://raw.communitydragon.org/latest/plugins/rcp-be-lol-game-data/global/default/v1/champion-chroma-images/887/887045.png",
          "mythicIcon": null,
          "wildRiftSell": {
            "startDate": "",
            "endDate": "",
            "description": "",
            "activityTitle": "",
            "price": "",
            "priceUnit": ""
          },
          "colors": [
            "#E58BA5",
            "#E58BA5"
          ]
        },
        {
          "id": 887046,
          "name": "青蛙雨衣 格温 丝雨",
          "sortName": "丝雨",
          "colorName": "白色",
          "tencent": {
            "price": 0,
            "priceType": "暂无",
            "priceStartDay": "",
            "priceEndDay": "",
            "description": "",
            "wildRiftSell": {
              "startDate": "",
              "endDate": "",
              "description": "",
              "activityTitle": "",
              "price": "",
              "priceUnit": ""
            }
          },
          "roit": {
            "price": 290,
            "priceType": "直售",
            "priceStartDay": "",
            "priceEndDay": "",
            "description": ""
          },
          "riotName": "青蛙雨衣 格温 丝雨",
          "chromasPath": "https://raw.communitydragon.org/latest/plugins/rcp-be-lol-game-data/global/default/v1/champion-chroma-images/887/887046.png",
          "mythicIcon": null,
          "wildRiftSell": {
            "startDate": "",
            "endDate": "",
            "description": "",
            "activityTitle": "",
            "price": "",
            "priceUnit": ""
          },
          "colors": [
            "#ECF9F8",
            "#ECF9F8"
          ]
        },
        {
          "id": 887047,
          "name": "青蛙雨衣 格温 夜雨",
          "sortName": "夜雨",
          "colorName": "黑色",
          "tencent": {
            "price": 0,
            "priceType": "暂无",
            "priceStartDay": "",
            "priceEndDay": "",
            "description": "",
            "wildRiftSell": {
              "startDate": "",
              "endDate": "",
              "description": "",
              "activityTitle": "",
              "price": "",
              "priceUnit": ""
            }
          },
          "roit": {
            "price": 290,
            "priceType": "直售",
            "priceStartDay": "",
            "priceEndDay": "",
            "description": ""
          },
          "riotName": "青蛙雨衣 格温 夜雨",
          "chromasPath": "https://raw.communitydragon.org/latest/plugins/rcp-be-lol-game-data/global/default/v1/champion-chroma-images/887/887047.png",
          "mythicIcon": null,
          "wildRiftSell": {
            "startDate": "",
            "endDate": "",
            "description": "",
            "activityTitle": "",
            "price": "",
            "priceUnit": ""
          },
          "colors": [
            "#27211C",
            "#27211C"
          ]
        }
      ],
      "version": {
        "push": "25.23",
        "update": "",
        "updateChinese": "",
        "updateName": "",
        "video": ""
      }
    },
    {
      "id": 887030,
      "name": "女帝 格温",
      "roitName": "Battle Queen Gwen",
      "sortName": null,
      "rarity": "史诗",
      "raritySubType": null,
      "price": null,
      "priceUnit": null,
      "skinline": "女帝无双",
      "universe": "女帝无双",
      "pushDate": "2024年8月28日",
      "splashPath": "https://raw.communitydragon.org/latest/plugins/rcp-be-lol-game-data/global/default/assets/characters/gwen/skins/skin30/images/gwen_splash_uncentered_30.skins_gwen_skin30.jpg",
      "splashHDPath": "",
      "squareePath": "https://raw.communitydragon.org/latest/plugins/rcp-be-lol-game-data/global/default/assets/characters/gwen/skins/skin30/images/gwen_splash_tile_30.skins_gwen_skin30.jpg",
      "iconPath": null,
      "centeredPath": "https://raw.communitydragon.org/latest/plugins/rcp-be-lol-game-data/global/default/assets/characters/gwen/skins/skin30/images/gwen_splash_centered_30.skins_gwen_skin30.jpg",
      "circlePath": "",
      "chromaPath": "https://raw.communitydragon.org/latest/plugins/rcp-be-lol-game-data/global/default/v1/champion-chroma-images/887/887030.png",
      "specialEditionPath": null,
      "loadingPath": "https://raw.communitydragon.org/latest/plugins/rcp-be-lol-game-data/global/default/assets/characters/gwen/skins/skin30/gwenloadscreen_30.skins_gwen_skin30.jpg",
      "loadingSpecialEditionPath": "",
      "backstory": "卡利戈，一个遥远的、古老的女帝之国，长期以来被认为已经消失在时间中。来自卡利戈的格温冲破了这个国家的保护云层，与伊莱西亚的其他国度重新建立了联系。她的前任——女帝伊苏尔德——相信格温的纯洁心灵和敏锐头脑会证实卡利戈的力量并与其他统治者们结盟——因为黑暗时代就在前方，只有一份坚定不移的盟约才能防止最坏的情况发生。 ",
      "accessories": [],
      "roit": {
        "price": 1350,
        "priceType": "直售",
        "priceStartDay": "",
        "priceEndDay": "",
        "description": ""
      },
      "tencentPrice": 8900,
      "icon": "",
      "tencent": {
        "price": 8900,
        "priceType": "限时直售",
        "priceTypeChinese": "13周年限定",
        "priceStartDay": "2024年8月29日",
        "priceEndDay": "2024年9月25日23:59",
        "description": "可在【凤舞无双宝典】1级随机女帝2024皮肤宝箱获取"
      },
      "chromas": [
        {
          "id": 887031,
          "name": "女帝 格温 纹章之刻印·英勇",
          "sortName": "纹章之刻印·英勇",
          "colorName": "红色",
          "tencent": {
            "price": 2000,
            "priceType": "礼包",
            "priceStartDay": "2024年8月29日",
            "priceEndDay": "2024年9月12日9:59",
            "description": "",
            "wildRiftSell": null
          },
          "roit": {
            "price": 290,
            "priceType": "直售",
            "priceStartDay": "",
            "priceEndDay": "",
            "description": ""
          },
          "riotName": "女帝 格温 纹章之刻印·英勇",
          "chromasPath": "https://raw.communitydragon.org/latest/plugins/rcp-be-lol-game-data/global/default/v1/champion-chroma-images/887/887031.png",
          "mythicIcon": null,
          "wildRiftSell": null,
          "colors": [
            "#D33528",
            "#D33528"
          ]
        },
        {
          "id": 887032,
          "name": "女帝 格温 纹章之刻印·坚毅",
          "sortName": "纹章之刻印·坚毅",
          "colorName": "黄色",
          "tencent": {
            "price": 2000,
            "priceType": "限时直售",
            "priceStartDay": "2024年8月29日",
            "priceEndDay": "2024年9月12日9:59",
            "description": "",
            "wildRiftSell": null
          },
          "roit": {
            "price": 290,
            "priceType": "直售",
            "priceStartDay": "",
            "priceEndDay": "",
            "description": ""
          },
          "riotName": "女帝 格温 纹章之刻印·坚毅",
          "chromasPath": "https://raw.communitydragon.org/latest/plugins/rcp-be-lol-game-data/global/default/v1/champion-chroma-images/887/887032.png",
          "mythicIcon": null,
          "wildRiftSell": null,
          "colors": [
            "#FFEE59",
            "#FFEE59"
          ]
        },
        {
          "id": 887033,
          "name": "女帝 格温 纹章之刻印·果决",
          "sortName": "纹章之刻印·果决",
          "colorName": "蓝色",
          "tencent": {
            "price": 0,
            "priceType": "臻彩",
            "priceStartDay": "2025年4月11日",
            "priceEndDay": "2025年5月5日",
            "description": "女帝和公主的优雅刻印活动",
            "wildRiftSell": null,
            "ExquisitePath": "https://www.ghostoact.com/static/arts/img/chroma/apwa5mnpn8wrd0x0t2mpapjg3hmw05g0.jpg"
          },
          "roit": {
            "price": 290,
            "priceType": "直售",
            "priceStartDay": "",
            "priceEndDay": "",
            "description": ""
          },
          "riotName": "女帝 格温 纹章之刻印·果决",
          "chromasPath": "https://raw.communitydragon.org/latest/plugins/rcp-be-lol-game-data/global/default/v1/champion-chroma-images/887/887033.png",
          "mythicIcon": null,
          "wildRiftSell": null,
          "colors": [
            "#2756CE",
            "#2756CE"
          ]
        },
        {
          "id": 887034,
          "name": "女帝 格温 纹章之刻印·强运",
          "sortName": "纹章之刻印·强运",
          "colorName": "粉色",
          "tencent": {
            "price": 0,
            "priceType": "暂无",
            "priceStartDay": "",
            "priceEndDay": "",
            "description": "",
            "wildRiftSell": null
          },
          "roit": {
            "price": 290,
            "priceType": "直售",
            "priceStartDay": "",
            "priceEndDay": "",
            "description": ""
          },
          "riotName": "女帝 格温 纹章之刻印·强运",
          "chromasPath": "https://raw.communitydragon.org/latest/plugins/rcp-be-lol-game-data/global/default/v1/champion-chroma-images/887/887034.png",
          "mythicIcon": null,
          "wildRiftSell": null,
          "colors": [
            "#E58BA5",
            "#E58BA5"
          ]
        },
        {
          "id": 887035,
          "name": "女帝 格温 纹章之刻印·威风",
          "sortName": "纹章之刻印·威风",
          "colorName": "青色",
          "tencent": {
            "price": 2000,
            "priceType": "限时直售",
            "priceStartDay": "2024年8月29日",
            "priceEndDay": "2024年9月12日9:59",
            "description": "",
            "wildRiftSell": null
          },
          "roit": {
            "price": 290,
            "priceType": "直售",
            "priceStartDay": "",
            "priceEndDay": "",
            "description": ""
          },
          "riotName": "女帝 格温 纹章之刻印·威风",
          "chromasPath": "https://raw.communitydragon.org/latest/plugins/rcp-be-lol-game-data/global/default/v1/champion-chroma-images/887/887035.png",
          "mythicIcon": null,
          "wildRiftSell": null,
          "colors": [
            "#73BFBE",
            "#73BFBE"
          ]
        },
        {
          "id": 887036,
          "name": "女帝 格温 纹章之刻印·飒爽",
          "sortName": "纹章之刻印·飒爽",
          "colorName": "紫色",
          "tencent": {
            "price": 2000,
            "priceType": "限时直售",
            "priceStartDay": "2024年8月29日",
            "priceEndDay": "2024年9月12日9:59",
            "description": "",
            "wildRiftSell": null
          },
          "roit": {
            "price": 290,
            "priceType": "直售",
            "priceStartDay": "",
            "priceEndDay": "",
            "description": ""
          },
          "riotName": "女帝 格温 纹章之刻印·飒爽",
          "chromasPath": "https://raw.communitydragon.org/latest/plugins/rcp-be-lol-game-data/global/default/v1/champion-chroma-images/887/887036.png",
          "mythicIcon": null,
          "wildRiftSell": null,
          "colors": [
            "#54209B",
            "#54209B"
          ]
        },
        {
          "id": 887037,
          "name": "女帝 格温 纹章之刻印·深谋",
          "sortName": "纹章之刻印·深谋",
          "colorName": "黑色",
          "tencent": {
            "price": 2000,
            "priceType": "限时直售",
            "priceStartDay": "2024年8月29日",
            "priceEndDay": "2024年9月12日9:59",
            "description": "",
            "wildRiftSell": null
          },
          "roit": {
            "price": 290,
            "priceType": "直售",
            "priceStartDay": "",
            "priceEndDay": "",
            "description": ""
          },
          "riotName": "女帝 格温 纹章之刻印·深谋",
          "chromasPath": "https://raw.communitydragon.org/latest/plugins/rcp-be-lol-game-data/global/default/v1/champion-chroma-images/887/887037.png",
          "mythicIcon": null,
          "wildRiftSell": null,
          "colors": [
            "#27211C",
            "#27211C"
          ]
        },
        {
          "id": 887038,
          "name": "女帝 格温 纹章之刻印·敏锐",
          "sortName": "纹章之刻印·敏锐",
          "colorName": "白色",
          "tencent": {
            "price": 0,
            "priceType": "臻彩",
            "priceStartDay": "2024年8月29日",
            "priceEndDay": "2024年9月12日9:59",
            "description": "皮肤成就 解锁女帝主题皮肤",
            "wildRiftSell": null,
            "ExquisitePath": "https://www.ghostoact.com/static/arts/img/chroma/a3yopk91zoqb2obiim2pejlbiqysp8zo.jpg"
          },
          "roit": {
            "price": 290,
            "priceType": "直售",
            "priceStartDay": "",
            "priceEndDay": "",
            "description": ""
          },
          "riotName": "女帝 格温 纹章之刻印·敏锐",
          "chromasPath": "https://raw.communitydragon.org/latest/plugins/rcp-be-lol-game-data/global/default/v1/champion-chroma-images/887/887038.png",
          "mythicIcon": null,
          "wildRiftSell": null,
          "colors": [
            "#ECF9F8",
            "#ECF9F8"
          ]
        }
      ],
      "version": {
        "push": "14.17",
        "update": "",
        "updateChinese": "",
        "updateName": "",
        "video": ""
      }
    },
    {
      "id": 887020,
      "name": "斗魂觉醒 格温",
      "roitName": "Soul Fighter Gwen",
      "sortName": null,
      "rarity": "史诗",
      "raritySubType": null,
      "price": null,
      "priceUnit": null,
      "skinline": "斗魂觉醒",
      "universe": "斗魂觉醒",
      "pushDate": "2023年8月3日",
      "splashPath": "https://raw.communitydragon.org/latest/plugins/rcp-be-lol-game-data/global/default/assets/characters/gwen/skins/skin20/images/gwen_splash_uncentered_20.jpg",
      "splashHDPath": "",
      "squareePath": "https://raw.communitydragon.org/latest/plugins/rcp-be-lol-game-data/global/default/assets/characters/gwen/skins/skin20/images/gwen_splash_tile_20.jpg",
      "iconPath": "",
      "centeredPath": "https://raw.communitydragon.org/latest/plugins/rcp-be-lol-game-data/global/default/assets/characters/gwen/skins/skin20/images/gwen_splash_centered_20.jpg",
      "circlePath": "",
      "chromaPath": "https://raw.communitydragon.org/latest/plugins/rcp-be-lol-game-data/global/default/v1/champion-chroma-images/887/887020.png",
      "specialEditionPath": null,
      "loadingPath": "https://raw.communitydragon.org/latest/plugins/rcp-be-lol-game-data/global/default/assets/characters/gwen/skins/skin20/gwenloadscreen_20.jpg",
      "loadingSpecialEditionPath": "https://raw.communitydragon.org/latest/plugins/rcp-be-lol-game-data/global/default/assets/characters/gwen/skins/skin20/gwenloadscreen_20_le.jpg",
      "backstory": "她去过世界的尽头……以及彼岸……去拯救她的朋友！根据我现在看到的排名表，她必须和这个朋友一决高下才能赢得这次武道大会！噢！我发誓，这不是故意安排的，伙计们。这可是实况电视节目！一个心怀友谊的少女拿着能够起死回生的剪子：有请格温！",
      "accessories": [],
      "roit": {
        "price": 1350,
        "priceType": "直售",
        "priceStartDay": "",
        "priceEndDay": "",
        "description": ""
      },
      "tencentPrice": 8900,
      "icon": "5940",
      "tencent": {
        "price": 8900,
        "priceType": "直售",
        "priceTypeChinese": "",
        "priceStartDay": "2023年8月4日10:00",
        "priceEndDay": "长期销售",
        "description": ""
      },
      "chromas": [
        {
          "id": 887021,
          "name": "斗魂觉醒 格温 烈之魂焰",
          "sortName": "烈之魂焰",
          "colorName": "红色",
          "tencent": {
            "price": 0,
            "priceType": "暂无",
            "priceStartDay": "",
            "priceEndDay": "",
            "description": "",
            "wildRiftSell": {
              "startDate": "",
              "endDate": "",
              "description": "",
              "activityTitle": "",
              "price": "",
              "priceUnit": ""
            }
          },
          "roit": {
            "price": 290,
            "priceType": "直售",
            "priceStartDay": "",
            "priceEndDay": "",
            "description": "这个炫彩曾在2023年期间作为礼包专属发布。"
          },
          "riotName": "斗魂觉醒 格温 烈之魂焰",
          "chromasPath": "https://raw.communitydragon.org/latest/plugins/rcp-be-lol-game-data/global/default/v1/champion-chroma-images/887/887021.png",
          "mythicIcon": null,
          "wildRiftSell": {
            "startDate": "",
            "endDate": "",
            "description": "",
            "activityTitle": "",
            "price": "",
            "priceUnit": ""
          },
          "colors": [
            "#D33528",
            "#D33528"
          ]
        },
        {
          "id": 887022,
          "name": "斗魂觉醒 格温 毅之魂焰",
          "sortName": "毅之魂焰",
          "colorName": "橙色",
          "tencent": {
            "price": 6300,
            "priceType": "橙色精萃",
            "priceStartDay": "2023年8月4日",
            "priceEndDay": "2023年8月18日9:59",
            "description": "",
            "wildRiftSell": {
              "startDate": "",
              "endDate": "",
              "description": "",
              "activityTitle": "",
              "price": "",
              "priceUnit": ""
            }
          },
          "roit": {
            "price": 290,
            "priceType": "直售",
            "priceStartDay": "",
            "priceEndDay": "",
            "description": ""
          },
          "riotName": "斗魂觉醒 格温 毅之魂焰",
          "chromasPath": "https://raw.communitydragon.org/latest/plugins/rcp-be-lol-game-data/global/default/v1/champion-chroma-images/887/887022.png",
          "mythicIcon": null,
          "wildRiftSell": {
            "startDate": "",
            "endDate": "",
            "description": "",
            "activityTitle": "",
            "price": "",
            "priceUnit": ""
          },
          "colors": [
            "#DF9117",
            "#DF9117"
          ]
        },
        {
          "id": 887023,
          "name": "斗魂觉醒 格温 狡之魂焰",
          "sortName": "狡之魂焰",
          "colorName": "蓝色",
          "tencent": {
            "price": 0,
            "priceType": "暂无",
            "priceStartDay": "",
            "priceEndDay": "",
            "description": "",
            "wildRiftSell": {
              "startDate": "",
              "endDate": "",
              "description": "",
              "activityTitle": "",
              "price": "",
              "priceUnit": ""
            }
          },
          "roit": {
            "price": 290,
            "priceType": "直售",
            "priceStartDay": "",
            "priceEndDay": "",
            "description": ""
          },
          "riotName": "斗魂觉醒 格温 狡之魂焰",
          "chromasPath": "https://raw.communitydragon.org/latest/plugins/rcp-be-lol-game-data/global/default/v1/champion-chroma-images/887/887023.png",
          "mythicIcon": null,
          "wildRiftSell": {
            "startDate": "",
            "endDate": "",
            "description": "",
            "activityTitle": "",
            "price": "",
            "priceUnit": ""
          },
          "colors": [
            "#2756CE",
            "#2756CE"
          ]
        },
        {
          "id": 887024,
          "name": "斗魂觉醒 格温 韧之魂焰",
          "sortName": "韧之魂焰",
          "colorName": "绿色",
          "tencent": {
            "price": 6300,
            "priceType": "橙色精萃",
            "priceStartDay": "2023年8月4日",
            "priceEndDay": "2023年8月18日9:59",
            "description": "",
            "wildRiftSell": {
              "startDate": "",
              "endDate": "",
              "description": "",
              "activityTitle": "",
              "price": "",
              "priceUnit": ""
            }
          },
          "roit": {
            "price": 290,
            "priceType": "直售",
            "priceStartDay": "",
            "priceEndDay": "",
            "description": ""
          },
          "riotName": "斗魂觉醒 格温 韧之魂焰",
          "chromasPath": "https://raw.communitydragon.org/latest/plugins/rcp-be-lol-game-data/global/default/v1/champion-chroma-images/887/887024.png",
          "mythicIcon": null,
          "wildRiftSell": {
            "startDate": "",
            "endDate": "",
            "description": "",
            "activityTitle": "",
            "price": "",
            "priceUnit": ""
          },
          "colors": [
            "#2DA130",
            "#2DA130"
          ]
        },
        {
          "id": 887025,
          "name": "斗魂觉醒 格温 飒之魂焰",
          "sortName": "飒之魂焰",
          "colorName": "青色",
          "tencent": {
            "price": 6300,
            "priceType": "橙色精萃",
            "priceStartDay": "2023年8月4日",
            "priceEndDay": "2023年8月18日9:59",
            "description": "",
            "wildRiftSell": {
              "startDate": "",
              "endDate": "",
              "description": "",
              "activityTitle": "",
              "price": "",
              "priceUnit": ""
            }
          },
          "roit": {
            "price": 290,
            "priceType": "直售",
            "priceStartDay": "",
            "priceEndDay": "",
            "description": ""
          },
          "riotName": "斗魂觉醒 格温 飒之魂焰",
          "chromasPath": "https://raw.communitydragon.org/latest/plugins/rcp-be-lol-game-data/global/default/v1/champion-chroma-images/887/887025.png",
          "mythicIcon": null,
          "wildRiftSell": {
            "startDate": "",
            "endDate": "",
            "description": "",
            "activityTitle": "",
            "price": "",
            "priceUnit": ""
          },
          "colors": [
            "#73BFBE",
            "#73BFBE"
          ]
        },
        {
          "id": 887026,
          "name": "斗魂觉醒 格温 魅之魂焰",
          "sortName": "魅之魂焰",
          "colorName": "紫色",
          "tencent": {
            "price": 6300,
            "priceType": "橙色精萃",
            "priceStartDay": "2023年8月4日",
            "priceEndDay": "2023年8月18日9:59",
            "description": "",
            "wildRiftSell": {
              "startDate": "",
              "endDate": "",
              "description": "",
              "activityTitle": "",
              "price": "",
              "priceUnit": ""
            }
          },
          "roit": {
            "price": 290,
            "priceType": "直售",
            "priceStartDay": "",
            "priceEndDay": "",
            "description": ""
          },
          "riotName": "斗魂觉醒 格温 魅之魂焰",
          "chromasPath": "https://raw.communitydragon.org/latest/plugins/rcp-be-lol-game-data/global/default/v1/champion-chroma-images/887/887026.png",
          "mythicIcon": null,
          "wildRiftSell": {
            "startDate": "",
            "endDate": "",
            "description": "",
            "activityTitle": "",
            "price": "",
            "priceUnit": ""
          },
          "colors": [
            "#9C68D7",
            "#9C68D7"
          ]
        },
        {
          "id": 887027,
          "name": "斗魂觉醒 格温 幻之魂焰",
          "sortName": "幻之魂焰",
          "colorName": "粉色",
          "tencent": {
            "price": 0,
            "priceType": "臻彩",
            "priceStartDay": "2024年12月10日",
            "priceEndDay": "长期开放",
            "description": "皮肤成就：解锁4款指定格温皮肤",
            "wildRiftSell": {
              "startDate": "",
              "endDate": "",
              "description": "",
              "activityTitle": "",
              "price": "",
              "priceUnit": ""
            },
            "ExquisitePath": "https://www.ghostoact.com/static/arts/img/chroma/auso2mc25t13evs1do3s12bsiredhnyk.jpg"
          },
          "roit": {
            "price": 290,
            "priceType": "直售",
            "priceStartDay": "",
            "priceEndDay": "",
            "description": ""
          },
          "riotName": "斗魂觉醒 格温 幻之魂焰",
          "chromasPath": "https://raw.communitydragon.org/latest/plugins/rcp-be-lol-game-data/global/default/v1/champion-chroma-images/887/887027.png",
          "mythicIcon": null,
          "wildRiftSell": {
            "startDate": "",
            "endDate": "",
            "description": "",
            "activityTitle": "",
            "price": "",
            "priceUnit": ""
          },
          "colors": [
            "#E58BA5",
            "#E58BA5"
          ]
        },
        {
          "id": 887028,
          "name": "斗魂觉醒 格温 灵之魂焰",
          "sortName": "灵之魂焰",
          "colorName": "珍珠",
          "tencent": {
            "price": 0,
            "priceType": "暂无",
            "priceStartDay": "",
            "priceEndDay": "",
            "description": "",
            "wildRiftSell": {
              "startDate": "",
              "endDate": "",
              "description": "",
              "activityTitle": "",
              "price": "",
              "priceUnit": ""
            }
          },
          "roit": {
            "price": 290,
            "priceType": "直售",
            "priceStartDay": "",
            "priceEndDay": "",
            "description": ""
          },
          "riotName": "斗魂觉醒 格温 灵之魂焰",
          "chromasPath": "https://raw.communitydragon.org/latest/plugins/rcp-be-lol-game-data/global/default/v1/champion-chroma-images/887/887028.png",
          "mythicIcon": null,
          "wildRiftSell": {
            "startDate": "",
            "endDate": "",
            "description": "",
            "activityTitle": "",
            "price": "",
            "priceUnit": ""
          },
          "colors": [
            "#DED6B0",
            "#DED6B0"
          ]
        },
        {
          "id": 887029,
          "name": "斗魂觉醒 格温 无限斗志",
          "sortName": "无限斗志",
          "colorName": "斗魂觉醒(2023)",
          "tencent": {
            "price": 35,
            "priceType": "神话商店",
            "priceStartDay": "2023年8月4日",
            "priceEndDay": "2023年8月18日9:59",
            "description": "斗魂觉醒(2023)",
            "wildRiftSell": {
              "startDate": "",
              "endDate": "",
              "description": "",
              "activityTitle": "",
              "price": "",
              "priceUnit": ""
            }
          },
          "roit": {
            "price": 35,
            "priceType": "神话商店",
            "priceStartDay": "",
            "priceEndDay": "",
            "description": "这个炫彩曾在斗魂觉醒(2023)活动期间作为战利品专属发布。"
          },
          "riotName": "斗魂觉醒 格温 无限斗志",
          "chromasPath": "https://raw.communitydragon.org/latest/plugins/rcp-be-lol-game-data/global/default/v1/champion-chroma-images/887/887029.png",
          "mythicIcon": "5935",
          "wildRiftSell": {
            "startDate": "",
            "endDate": "",
            "description": "",
            "activityTitle": "",
            "price": "",
            "priceUnit": ""
          },
          "colors": [
            "#C8D0CE",
            "#AF65D1"
          ]
        }
      ],
      "version": {
        "push": "13.15",
        "update": "",
        "updateChinese": "",
        "updateName": "",
        "video": "26.01"
      }
    }
  ]
}